escriptorium_fetcher/__init__.py
escriptorium_fetcher/main.py
escriptorium_fetcher-0.1.1.dist-info/entry_points.txt
escriptorium_fetcher-0.1.1.dist-info/WHEEL
escriptorium_fetcher-0.1.1.dist-info/METADATA
escriptorium_fetcher-0.1.1.dist-info/RECORD
