Metadata-Version: 2.1
Name: escriptorium-fetcher
Version: 0.1.1
Summary: 
Author: apjanco
Author-email: apjanco@gmail.com
Requires-Python: >=3.10,<4.0
Classifier: Programming Language :: Python :: 3
Classifier: Programming Language :: Python :: 3.10
Requires-Dist: escriptorium-connector (>=0.2.6,<0.3.0)
Requires-Dist: rich (>=13.7.0,<14.0.0)
Requires-Dist: srsly (>=2.4.8,<3.0.0)
Requires-Dist: typer[all] (>=0.9.0,<0.10.0)
